odd_div.sv
// -----------------------------------------------------------------------------
// Module: odd_div
// Description:
//   Parameterizable clock divider that divides the input clock (clk) by an odd or
//   even value specified by div_val. Generates clkout with ~50% duty cycle for
//   both odd and even division values.
//
// Ports:
//   input  logic resetn   - Active-low reset. Resets all internal registers.
//   input  logic [7:0] div_val - Division value (odd/even supported).
//   input  logic clk      - Input clock to be divided.
//   output logic clkout   - Output divided clock.
//
// Internal Signals:
//   logic [7:0] cnt       - Counts clock cycles up to div_val - 1.
//   logic toggle1, toggle2- Toggles for generating clkout with correct duty cycle.
//   logic [6:0] half_div  - Half of div_val (integer division).
//   logic odd_even        - 1 if div_val is odd, 0 if even.
//   logic [7:0] div_val_lat - Latched division value for stable operation.
//
// Functionality:
//   - On reset, all signals are initialized.
//   - div_val is latched at the start of each division cycle.
//   - For odd div_val: toggle1 toggles every div_val cycles, toggle2 toggles at midpoint.
//   - For even div_val: toggle1 toggles every div_val/2 cycles.
//   - clkout is generated by combining toggle1 and toggle2 for odd division, or just toggle1 for even division.
//
// Output Logic:
//   clkout = (odd_even) ? (toggle1 ^ toggle2) : toggle1;
// -----------------------------------------------------------------------------

module odd_div (
    input logic resetn,
    input logic [7:0] div_val,
    input logic clk,
    output logic clkout
);
    logic [7:0] cnt;
    logic toggle1;
    logic toggle2;
    logic [6:0] half_div;
    logic odd_even;
    logic [7:0] div_val_lat;
    assign half_div = (cnt == 0)? div_val[7:1]: div_val_lat[7:1]; // Integer division by 2
    assign odd_even = (cnt == 0)? div_val[0]: div_val_lat[0]; // 1 if odd, 0 if even
    // For odd div_val, toggle1 toggles every div_val cycles
    // For even div_val, toggle1 toggles every div_val/2 cycles
    always_ff @(posedge clk or negedge resetn) begin
        if (!resetn) begin
            div_val_lat <= 0;
        end else if (cnt == 0) begin
            div_val_lat <= div_val;
        end
    end
    always_ff @(posedge clk or negedge resetn) begin
        if (!resetn) begin
            cnt <= 0;
            toggle1 <= 1;
            toggle2 <= 1;
        end else begin 
            if (cnt == 0 & odd_even == 1'b1) begin
                toggle1 <= ~toggle1;
            end
            else if (((cnt == 0)|cnt == (half_div))  & odd_even == 1'b0) begin
                toggle1 <= ~toggle1;
            end
            cnt <= (cnt == div_val_lat - 1) ? 0 : cnt + 1;
        end
    end
    always_ff @(negedge clk or negedge resetn) begin
        if (!resetn) begin
            toggle2 <= 1;
        end else begin 
            if (cnt == (half_div + 1)) begin
                toggle2 <= ~toggle2;
            end
        end
    end
assign clkout = (odd_even) ? (toggle1 ^ toggle2) : toggle1;
endmodule

tb_odd.sv
`timescale 1ns/1ps

// -----------------------------------------------------------------------------
// Testbench: tb_odd_dv
// Description:
//   Testbench for the odd_div module. It verifies the clock divider functionality
//   for various odd and even division values. The testbench applies reset and
//   changes div_val to different values, monitoring the output clkout.
//
// Scenarios Tested:
//   1. div_val = 3 (odd)
//   2. div_val = 5 (odd)
//   3. div_val = 7 (odd)
//   4. div_val = 4 (even)
//   5. div_val = 6 (even)
//   6. div_val = 8 (even)
//
// Features:
//   - Generates a 100MHz clock.
//   - Applies reset and sets div_val for each scenario.
//   - Dumps waveform to tb_odd_dv.vcd for analysis.
//   - Monitors and displays key signals during simulation.
// -----------------------------------------------------------------------------

module tb_odd_dv;

logic resetn;
logic [7:0] div_val;
logic clk;
logic clkout;

odd_div uut (
    .resetn(resetn),
    .div_val(div_val),
    .clk(clk),
    .clkout(clkout)
);

// Clock generation
initial clk = 0;
always #5 clk = ~clk; // 100MHz clock

// Test sequence
initial begin
    $dumpfile("tb_odd_dv.vcd");
	$dumpvars(0,tb_odd_dv);
    $display("Starting odd_div testbench...");
    resetn = 0;
    div_val = 3;
    #20;
    resetn = 1;
    #100;
    $display("Test 1: div_val = 3");

    //resetn = 0;
    div_val = 5;
    #20;
    resetn = 1;
    #100;
    $display("Test 2: div_val = 5");

    //resetn = 0;
    div_val = 7;
    #20;
    resetn = 1;
    #200;
    $display("Test 3: div_val = 7");

    //resetn = 0;
    div_val = 4;
    #20;
    resetn = 1;
    #100;
    $display("Test 4: div_val = 4");

    //resetn = 0;
    div_val = 6;
    #20;
    resetn = 1;
    #100;
    $display("Test 5: div_val = 6");

    //resetn = 0;
    div_val = 8;
    #20;
    resetn = 1;
    #400;
    $display("Test 6: div_val = 8");

    $finish;
end

// Optional: monitor signals
initial begin
    $monitor("Time=%0t | resetn=%b | div_val=%0d | clkout=%b", $time, resetn, div_val, clkout);
end

initial begin
    #2000;
    $finish;
end

endmodule

tb_odd_dv.vcd
$date
	Sat Sep 20 16:39:57 2025
$end
$version
	Icarus Verilog
$end
$timescale
	1ps
$end
$scope module tb_odd_dv $end
$var wire 1 ! clkout $end
$var reg 1 " clk $end
$var reg 8 # div_val [7:0] $end
$var reg 1 $ resetn $end
$scope module uut $end
$var wire 1 " clk $end
$var wire 8 % div_val [7:0] $end
$var wire 1 $ resetn $end
$var wire 1 & odd_even $end
$var wire 7 ' half_div [6:0] $end
$var wire 1 ! clkout $end
$var reg 8 ( cnt [7:0] $end
$var reg 8 ) div_val_lat [7:0] $end
$var reg 1 * toggle1 $end
$var reg 1 + toggle2 $end
$upscope $end
$upscope $end
$enddefinitions $end
$comment Show the parameter values. $end
$dumpall
$end
#0
$dumpvars
1+
1*
b0 )
b0 (
b1 '
1&
b11 %
0$
b11 #
0"
0!
$end
#5000
1"
#10000
0"
#15000
1"
#20000
0"
1$
#25000
1!
b1 (
0*
b11 )
1"
#30000
0"
#35000
b10 (
1"
#40000
0!
0+
0"
#45000
b0 (
1"
#50000
0"
#55000
1!
b1 (
1*
1"
#60000
0"
#65000
b10 (
1"
#70000
0!
1+
0"
#75000
b0 (
1"
#80000
0"
#85000
1!
b1 (
0*
1"
#90000
0"
#95000
b10 (
1"
#100000
0!
0+
0"
#105000
b0 (
1"
#110000
0"
#115000
1!
b1 (
1*
1"
#120000
0"
b101 #
b101 %
#125000
b10 (
1"
#130000
0!
1+
0"
#135000
b10 '
b0 (
1"
#140000
0"
#145000
1!
b1 (
0*
b101 )
1"
#150000
0"
#155000
b10 (
1"
#160000
0"
#165000
b11 (
1"
#170000
0!
0+
0"
#175000
b100 (
1"
#180000
0"
#185000
b0 (
1"
#190000
0"
#195000
1!
b1 (
1*
1"
#200000
0"
#205000
b10 (
1"
#210000
0"
#215000
b11 (
1"
#220000
0!
1+
0"
#225000
b100 (
1"
#230000
0"
#235000
b0 (
1"
#240000
b11 '
0"
b111 #
b111 %
#245000
1!
b1 (
0*
b111 )
1"
#250000
0"
#255000
b10 (
1"
#260000
0"
#265000
b11 (
1"
#270000
0"
#275000
b100 (
1"
#280000
0!
0+
0"
#285000
b101 (
1"
#290000
0"
#295000
b110 (
1"
#300000
0"
#305000
b0 (
1"
#310000
0"
#315000
1!
b1 (
1*
1"
#320000
0"
#325000
b10 (
1"
#330000
0"
#335000
b11 (
1"
#340000
0"
#345000
b100 (
1"
#350000
0!
1+
0"
#355000
b101 (
1"
#360000
0"
#365000
b110 (
1"
#370000
0"
#375000
b0 (
1"
#380000
0"
#385000
1!
b1 (
0*
1"
#390000
0"
#395000
b10 (
1"
#400000
0"
#405000
b11 (
1"
#410000
0"
#415000
b100 (
1"
#420000
0!
0+
0"
#425000
b101 (
1"
#430000
0"
#435000
b110 (
1"
#440000
0"
#445000
b0 (
1"
#450000
0"
#455000
1!
b1 (
1*
1"
#460000
0"
b100 #
b100 %
#465000
b10 (
1"
#470000
0"
#475000
b11 (
1"
#480000
0"
#485000
b100 (
1"
#490000
0!
1+
0"
#495000
b101 (
1"
#500000
0"
#505000
b110 (
1"
#510000
0"
#515000
1!
b10 '
0&
b0 (
1"
#520000
0"
#525000
0!
b1 (
0*
b100 )
1"
#530000
0"
#535000
b10 (
1"
#540000
0"
#545000
1!
b11 (
1*
1"
#550000
0+
0"
#555000
b0 (
1"
#560000
0"
#565000
0!
b1 (
0*
1"
#570000
0"
#575000
b10 (
1"
#580000
0"
b110 #
b110 %
#585000
1!
b11 (
1*
1"
#590000
1+
0"
#595000
b11 '
b0 (
1"
#600000
0"
#605000
0!
b1 (
0*
b110 )
1"
#610000
0"
#615000
b10 (
1"
#620000
0"
#625000
b11 (
1"
#630000
0"
#635000
1!
b100 (
1*
1"
#640000
0+
0"
#645000
b101 (
1"
#650000
0"
#655000
b0 (
1"
#660000
0"
#665000
0!
b1 (
0*
1"
#670000
0"
#675000
b10 (
1"
#680000
0"
#685000
b11 (
1"
#690000
0"
#695000
1!
b100 (
1*
1"
#700000
1+
0"
b1000 #
b1000 %
#705000
b101 (
1"
#710000
0"
#715000
b100 '
b0 (
1"
#720000
0"
#725000
0!
b1 (
0*
b1000 )
1"
#730000
0"
#735000
b10 (
1"
#740000
0"
#745000
b11 (
1"
#750000
0"
#755000
b100 (
1"
#760000
0"
#765000
1!
b101 (
1*
1"
#770000
0+
0"
#775000
b110 (
1"
#780000
0"
#785000
b111 (
1"
#790000
0"
#795000
b0 (
1"
#800000
0"
#805000
0!
b1 (
0*
1"
#810000
0"
#815000
b10 (
1"
#820000
0"
#825000
b11 (
1"
#830000
0"
#835000
b100 (
1"
#840000
0"
#845000
1!
b101 (
1*
1"
#850000
1+
0"
#855000
b110 (
1"
#860000
0"
#865000
b111 (
1"
#870000
0"
#875000
b0 (
1"
#880000
0"
#885000
0!
b1 (
0*
1"
#890000
0"
#895000
b10 (
1"
#900000
0"
#905000
b11 (
1"
#910000
0"
#915000
b100 (
1"
#920000
0"
#925000
1!
b101 (
1*
1"
#930000
0+
0"
#935000
b110 (
1"
#940000
0"
#945000
b111 (
1"
#950000
0"
#955000
b0 (
1"
#960000
0"
#965000
0!
b1 (
0*
1"
#970000
0"
#975000
b10 (
1"
#980000
0"
#985000
b11 (
1"
#990000
0"
#995000
b100 (
1"
#1000000
0"
#1005000
1!
b101 (
1*
1"
#1010000
1+
0"
#1015000
b110 (
1"
#1020000
0"
#1025000
b111 (
1"
#1030000
0"
#1035000
b0 (
1"
#1040000
0"
#1045000
0!
b1 (
0*
1"
#1050000
0"
#1055000
b10 (
1"
#1060000
0"
#1065000
b11 (
1"
#1070000
0"
#1075000
b100 (
1"
#1080000
0"
#1085000
1!
b101 (
1*
1"
#1090000
0+
0"
#1095000
b110 (
1"
#1100000
0"
#1105000
b111 (
1"
#1110000
0"
#1115000
b0 (
1"
